drf_dynamic_serializers/__init__.py
drf_dynamic_serializers/apps.py
drf_dynamic_serializers/conf.py
drf_dynamic_serializers/exceptions.py
drf_dynamic_serializers/mixins.py
drf_dynamic_serializers/serializers.py
drf_dynamic_serializers/views.py
drf_dynamic_serializers-1.0.dist-info/LICENSE
drf_dynamic_serializers-1.0.dist-info/METADATA
drf_dynamic_serializers-1.0.dist-info/WHEEL
drf_dynamic_serializers-1.0.dist-info/top_level.txt
drf_dynamic_serializers-1.0.dist-info/RECORD
