Metadata-Version: 2.1
Name: drf-dynamic-serializers
Version: 1.0
Summary: Dynamic serializers for the Django REST Framework
Home-page: https://github.com/csdenboer/drf-dynamic-serializers
Author: Christian den Boer
License: MIT
Project-URL: Documentation, https://drf-dynamic-serializers.readthedocs.io/
Project-URL: Source, https://github.com/csdenboer/drf-dynamic-serializers
Project-URL: Tracker, https://github.com/csdenboer/drf-dynamic-serializers/issues
Platform: UNKNOWN
Classifier: Development Status :: 5 - Production/Stable
Classifier: Environment :: Web Environment
Classifier: Framework :: Django
Classifier: Framework :: Django :: 2.2
Classifier: Framework :: Django :: 3.0
Classifier: Framework :: Django :: 3.1
Classifier: Programming Language :: Python
Classifier: Programming Language :: Python :: 3
Classifier: Programming Language :: Python :: 3.6
Classifier: Programming Language :: Python :: 3.7
Classifier: Programming Language :: Python :: 3.8
Classifier: License :: OSI Approved :: MIT License
Classifier: Operating System :: OS Independent
Classifier: Topic :: Internet :: WWW/HTTP
Classifier: Topic :: Software Development :: Libraries :: Python Modules
Requires-Python: >=3.6
Requires-Dist: django (>=2.2)
Requires-Dist: djangorestframework (>=3.10.3)
Requires-Dist: django-appconf (>=1.0.4)
